example_package_amirdubhub/__init__.py
example_package_amirdubhub/example.py
example_package_amirdubhub-0.0.5.dist-info/LICENSE
example_package_amirdubhub-0.0.5.dist-info/METADATA
example_package_amirdubhub-0.0.5.dist-info/WHEEL
example_package_amirdubhub-0.0.5.dist-info/top_level.txt
example_package_amirdubhub-0.0.5.dist-info/RECORD
