Metadata-Version: 2.1
Name: example-package-amirdubhub
Version: 0.0.5
Summary: A small example package
Author-email: Example Author <author@example.com>
License: Copyright (c) 2018 The Python Packaging Authority        
Project-URL: Homepage, https://github.com/pypa/sampleproject
Project-URL: Bug Tracker, https://github.com/pypa/sampleproject/issues
Classifier: Programming Language :: Python :: 3
Classifier: License :: OSI Approved :: MIT License
Classifier: Operating System :: OS Independent
Requires-Python: >=3.7
License-File: LICENSE
Requires-Dist: requests (==2.28.1)
